es_distributed/__init__.py
es_distributed/dist.py
es_distributed/es.py
es_distributed/main.py
es_distributed/optimizers.py
es_distributed/policies.py
es_distributed/tabular_logger.py
es_distributed/tf_util.py
es_distributed-0.1.0.dev0.dist-info/DESCRIPTION.rst
es_distributed-0.1.0.dev0.dist-info/METADATA
es_distributed-0.1.0.dev0.dist-info/RECORD
es_distributed-0.1.0.dev0.dist-info/WHEEL
es_distributed-0.1.0.dev0.dist-info/metadata.json
es_distributed-0.1.0.dev0.dist-info/top_level.txt
