Metadata-Version: 2.0
Name: es-distributed
Version: 0.1.0.dev0
Summary: UNKNOWN
Home-page: UNKNOWN
Author: UNKNOWN
Author-email: UNKNOWN
License: UNKNOWN
Platform: UNKNOWN
Requires-Dist: click
Requires-Dist: grpcio (==1.2.1)
Requires-Dist: gym (==0.10.5)
Requires-Dist: h5py
Requires-Dist: protobuf (==3.3.0)
Requires-Dist: psutil
Requires-Dist: redis
Requires-Dist: tensorflow (==1.3.0)
